ECC/__init__.py
ECC/aes.py
ECC/benchmark.py
ECC/curves.py
ECC/ecc.py
ECC/gf2m_curves.py
ECC/sha512.py
ECCryptography-0.0.1.dist-info/LICENSE
ECCryptography-0.0.1.dist-info/METADATA
ECCryptography-0.0.1.dist-info/WHEEL
ECCryptography-0.0.1.dist-info/top_level.txt
ECCryptography-0.0.1.dist-info/RECORD
