Metadata-Version: 2.1
Name: ECCryptography
Version: 0.0.1
Summary: Elliptic Curve Cryptography for public key encryption and ECDSA. Elliptic Cryptography Diffie Hellman Key Exchange with AES, and Sha512
Author-email: Taha Canturk <kibnakanoto@protonmail.com>
Project-URL: Homepage, https://github.com/kibnakamoto/ECC
Project-URL: Issues, https://github.com/kibnakamoto/ECC/issues
Classifier: Programming Language :: Python :: 3
Classifier: License :: OSI Approved :: GNU General Public License (GPL)
Classifier: Operating System :: OS Independent
Requires-Python: >=3.9
License-File: LICENSE
Requires-Dist: numpy>=1.26.4
